tidb_vector/__init__.py
tidb_vector/constants.py
tidb_vector/integrations/__init__.py
tidb_vector/integrations/utils.py
tidb_vector/integrations/vector_client.py
tidb_vector/peewee/__init__.py
tidb_vector/peewee/adaptor.py
tidb_vector/peewee/vector_type.py
tidb_vector/sqlalchemy/__init__.py
tidb_vector/sqlalchemy/adaptor.py
tidb_vector/sqlalchemy/vector_type.py
tidb_vector/utils.py
tidb_vector-0.0.15.dist-info/LICENSE
tidb_vector-0.0.15.dist-info/METADATA
tidb_vector-0.0.15.dist-info/WHEEL
tidb_vector-0.0.15.dist-info/RECORD
