Metadata-Version: 2.1
Name: tidb-vector
Version: 0.0.15
Summary: A Python client for TiDB Vector
License: Apache-2.0
Author: IANTHEREAL
Author-email: argregoryian@gmail.com
Requires-Python: >=3.9,<4.0
Classifier: License :: OSI Approved :: Apache Software License
Classifier: Programming Language :: Python :: 3
Classifier: Programming Language :: Python :: 3.9
Classifier: Programming Language :: Python :: 3.10
Classifier: Programming Language :: Python :: 3.11
Classifier: Programming Language :: Python :: 3.12
Classifier: Programming Language :: Python :: 3.13
Provides-Extra: client
Requires-Dist: SQLAlchemy (>=1.4,<3) ; extra == "client"
Requires-Dist: numpy (>=1,<3)
